Workbook
Name D_GRAND: '5. Pricing — Hosting'!$D$17
Name I_GRAND: '4. Pricing — Build'!$I$67
Name J_GRAND: '4. Pricing — Build'!$J$67

Sheet 1. Cover
B2: BLUE CORAL
B3: Powered by ADNS · Enterprise web & digital experience studio
B7: PROPOSAL & QUOTATION
B8: SAM Tuyen Lam Website Consolidation Programme
B12: One master brand · three properties · three languages · three booking flows
B15: PREPARED FOR SAM Tuyen Lam Hospitality Group | F15: REFERENCE BC-2026-0526-SAM · Issued 26 May 2026 · Valid until 25 June 2026
B20: PROGRAMME INVESTMENT AT A GLANCE
B22: PHASE 1 — DESIGN & BUILD | E22: PHASE 2 — HOSTING & SUPPORT (Y1) | H22: TOTAL PROGRAMME — Year 1
B23: ='4. Pricing — Build'!$I$67 -> 841891050 | E23: ='5. Pricing — Hosting'!$D$17 -> 66000000 | H23: ='4. Pricing — Build'!$I$67+'5. Pricing — Hosting'!$D$17 -> 907891050
B24: ='4. Pricing — Build'!$J$67 -> 32380.425 | E24: 12 months · VAT included | H24: =('4. Pricing — Build'!$I$67+'5. Pricing — Hosting'!$D$17)/26000 -> 34918.887
B27: ENGAGEMENT CONTEXT
B28: Client | D28: SAM Tuyen Lam Hospitality Group — Golf Course, Swiss-Belresort, Villa
B29: Primary Domain | D29: samtuyenlam.com.vn (consolidation of 4 legacy domains)
B30: Reference Style | D30: Hoiana.com (multi-property architecture) × NamiaRiverRetreat.com (emotional, healing tone)
B31: Languages | D31: Vietnamese · English · Korean
B32: Booking Flows | D32: Golf → VNPay · Swiss-Belresort → Hotel Link → Smile PMS · Villa → Lead capture
B33: Engagement | D33: Strategy, Design, Build, Migrate, Launch + 12-month Managed Services
B34: Delivery | D34: 20 weeks (5 months) from kickoff to launch · 4-week post-launch hypercare
B37: CONTACT & APPROVALS
B38: Prepared by | D38: Ms. Uyen Tran — Account Director, Blue Coral
B39: Approved by | D39: Mr. Nguyen — Managing Director, ADNS | H39: nguyen@bluecoral.vn · +84 979 477 101
B40: Client sponsor | D40: Mr. / Ms. ________________ (SAM Tuyen Lam) | H40: Date of signature: ____ / ____ / 2026
B44: This proposal is commercially confidential. Pricing and scope herein are valid for 30 days from the issue date.

Sheet 2. Executive Summary
B1: BLUE CORAL ▍ Powered by ADNS · 8/7D Phan Huy Ich, Tan Binh, Ho Chi Minh City · +84 979 477 101 · hello@bluecoral.vn
B3: Executive Summary
B5: 01 · ENGAGEMENT OVERVIEW
B6: SAM Tuyen Lam currently operates four disconnected websites — one per property and one legacy 360° VR portal. Each runs on different infrastructure, lacks a unified brand voice, and presents fragmented booking journeys to a global audience. This programme consolidates the four sites into a single master experience at samtuyenlam.com.vn, modelled on Hoiana's multi-property architecture and Namia River Retreat's emotional, healing tone. The new platform will deliver an Alpine-retreat narrative across three properties, three languages (VI / EN / KO), and three independent booking flows — with the marketing team in full control of campaigns through a permission-managed CMS.
B8: 02 · STRATEGIC OBJECTIVES
B9: BRAND CONSOLIDATION | E9: CONVERSION LIFT | H9: INTERNATIONAL REACH
B10: Unify 4 fragmented sites under one master brand narrative — Alpine retreat, healing, enduring love. | E10: Persistent property-aware "Book" CTAs, friction-free booking journeys, direct-booking incentives. | H10: Trilingual VI/EN/KO with Swiss-Belresort identity surfaced for inbound EN/KO traffic.
B12: MARKETING AUTONOMY | E12: PERFORMANCE & TRUST
B13: Role-based CMS lets Marketing publish offers, blog, news, banners, pop-ups without engineering tickets. | E13: Core Web Vitals green, WCAG-AA accessibility, hardened security (post-incident posture), full backup & DR.
B16: 03 · SCOPE AT A GLANCE — PROPERTY MAP
B17: Property | C17: Domain Path | D17: Booking System | F17: Primary Audience | H17: Templates Delivered
B18: SAM Tuyen Lam Golf Course | C18: /samtuyenlamgolf | D18: VNPay (booking → PMS) | F18: Golfers · Couples | H18: 1 Overview + 18-Hole + Coaching + Club House + Gallery + Booking
B19: Swiss-Belresort Tuyen Lam | C19: /swiss-belresorttuyenlam | D19: Hotel Link → Smile PMS | F19: 4★+ International · Wellness · MICE | H19: 1 Property + 7 Room Types + Spa + MICE + Dining + Gallery + Booking
B20: SAM Tuyen Lam Villa | C20: /samtuyenlamvilla | D20: Lead capture (temporarily closed) | F20: Future launch · Newsletter audience | H20: 1 Teaser + 5 Room Type design templates (no booking dev)
B22: 04 · PROGRAMME INVESTMENT
B23: # | C23: Phase | D23: Description | H23: Investment (VND) | J23: Investment (USD)
B24: 1 | C24: Design & Build | D24: Discovery · IA · Visual Design · 14 page templates · Booking integrations · CMS · Multi-language · SEO · QA · Launch · 4-week hypercare | H24: ='4. Pricing — Build'!$I$67 -> 841891050 | J24: ='4. Pricing — Build'!$J$67 -> 32380.425
B25: 2 | C25: Hosting & Support | D25: Year 1 — Enterprise hosting · CDN · SSL · WAF · 20 hrs/month managed services | H25: ='5. Pricing — Hosting'!$D$17 -> 66000000 | J25: —
B26: TOTAL PROGRAMME — Year 1 (VAT included) | H26: ='4. Pricing — Build'!$I$67+'5. Pricing — Hosting'!$D$17 -> 907891050 | J26: =('4. Pricing — Build'!$I$67+'5. Pricing — Hosting'!$D$17)/26000 -> 34918.887
B28: 05 · DELIVERY ROADMAP
B29: Milestone | C29: Phase | F29: Duration | G29: Key Deliverables
B30: M0 | C30: Discovery & Foundation | F30: Weeks 1-2 | G30: Sitemap signoff · Content audit · Brand narrative outline
B31: M1 | C31: Design | F31: Weeks 3-8 | G31: Design system + 14 visual templates approved
B32: M2 | C32: Build | F32: Weeks 9-14 | G32: Front-end · Back-end · CMS · Multi-language operational
B33: M3 | C33: Integration | F33: Weeks 15-18 | G33: VNPay · Hotel Link/Smile · 360° · Live chat · Analytics live
B34: M4 | C34: QA, UAT & Launch | F34: Weeks 19-20 | G34: 301 redirects · Security · Go-live · 4-week hypercare
B35: M5+ | C35: Hosting & Managed Services | F35: 12 Months | G35: SLA-backed support · backups · monitoring · monthly reports

Sheet 3. Scope of Work
B1: BLUE CORAL ▍ Powered by ADNS · 8/7D Phan Huy Ich, Tan Binh, Ho Chi Minh City · +84 979 477 101 · hello@bluecoral.vn
B3: Scope of Work — Detailed Deliverables
B5: The scope below is organised by workstream. Each line is a discrete deliverable with a defined acceptance output. All items are included in the Phase 1 investment unless explicitly marked optional.
B7: # | C7: Deliverable | D7: Description | E7: Acceptance Output
B8: A · DISCOVERY & BRAND FOUNDATION
B9: A.1 | C9: Stakeholder workshops & content audit | D9: On-site discovery with property GMs, marketing, IT, revenue. Inventory and quality-grade all assets across 4 legacy domains. | E9: Discovery report + asset inventory
B10: A.2 | C10: Information architecture & sitemap | D10: Master sitemap for 1 brand × 3 properties × 3 languages. URL strategy (clean, property-scoped, hreflang-ready). | E10: Approved sitemap + URL map
B11: A.3 | C11: Brand narrative & content strategy | D11: Brand storyline anchored on "Lost in nature, founding you" — nature, stillness, healing, enduring love. Tone guidelines, voice rules, lexicon. | E11: Brand narrative doc + tone guide
B12: A.4 | C12: Design system & component library | D12: Typography, colour, photographic mood, iconography, UI components (cards, hero, navigation, forms, modals). | E12: Figma design system file
B13: B · PAGE TEMPLATES — BRAND HOME
B14: B.1 | C14: Brand Home (master) | D14: Sticky header · Full-screen hero video · Brand narrative block · 3 property gateways · 3 experience pillars · Featured offers grid · Audience-segment quick links · Gallery teaser · Blog & newsletter · Footer. | E14: Responsive template — VI/EN/KO
B15: C · PAGE TEMPLATES — GOLF PROPERTY
B16: C.1 | C16: Golf overview & sub-pages | D16: 6 blocks: Hero · Course intro · 18-hole / Coaching / Club House · Golf-lifestyle experiences · Gallery + 360° · Final CTA. Club House nested children (Restaurant · Rooms · Pro Shop). | E16: Responsive template + 3 sub-pages
B17: D · PAGE TEMPLATES — SWISS-BELRESORT
B18: D.1 | C18: Resort overview | D18: 7 blocks: Hero + Swiss-Bel identity · 151-room intro · Room grid · Spa & Wellness · Dining · MICE · Experiences · Gallery + 360° · Final CTA. | E18: Responsive template
B19: D.2 | C19: Room Type pages (×3) | D19: Deluxe Mountain View · Deluxe Golf View · Studio Mountain View · Family Deluxe Mountain View · King Suite Mountain View · Royal Suite Mountain View · Standard. | E19: 3 detail templates with 360°
B20: D.3 | C20: Spa & Wellness | D20: Curated wellness journeys, not service list. | E20: Sub-page
B21: D.4 | C21: Dining | D21: Restaurant & bar storytelling, menu module. | E21: Sub-page
B22: D.5 | C22: MICE & Events | D22: Venue specs, capacity tables, RFP form. | E22: Sub-page + lead form
B23: E · PAGE TEMPLATES — VILLA
B24: E.1 | C24: Villa teaser (Coming Soon) | D24: Brand storytelling, "Love Trekk-in / Forest Service Hub" narrative, lead-capture form. No live booking. | E24: Responsive template
B25: E.2 | C25: Villa Room Type design templates (×1) | D25: Standard · Deluxe Lake View · Deluxe Garden View · Suite Lake View · (1 reserve). Design only; build deferred until soft launch. | E25: 1 Figma templates (design-only)
B26: F · SHARED PAGES
B27: F.1 | C27: About Us — brand story | D27: Master-brand origin, founding philosophy, leadership. | E27: Template
B28: F.2 | C28: Experiences (unified) | D28: Wellness · Golf lifestyle · Healing — three editorial pillars shared across properties. | E28: Template + CMS taxonomy
B29: F.3 | C29: Offers & Packages | D29: Filterable by property and audience; experience-led naming (no discount-only). | E29: Template + filtering UI
B30: F.4 | C30: Blog / News — list | D30: CMS-driven, 3-pillar taxonomy, infinite-scroll or pagination. | E30: Template
B31: F.5 | C31: Blog / News — article | D31: SEO-optimised, social-share, related cross-sells to properties & offers. | E31: Template
B32: F.6 | C32: Careers | D32: Open positions list, structured-data JobPosting, application form. | E32: Template
B33: F.7 | C33: Contact | D33: Property-routed forms, map, hotline, Zalo/Messenger, contact-by-purpose. | E33: Template + 3 forms
B34: F.8 | C34: Search | D34: Site-wide search across properties, offers, blog. Suggestion + filter. | E34: Search module + index
B35: F.9 | C35: Information pages | D35: Privacy policy, Terms, Cookie policy, 404, FAQ. | E35: 5 templates
B36: G · BOOKING INTEGRATIONS
B37: G.1 | C37: Golf → VNPay | D37: Tee-time selection · greens-fee calc · VNPay payment · email confirmation · PMS push (data spec to be confirmed by VNPay). | E37: End-to-end booking flow live
B38: G.2 | C38: Swiss-Belresort → Hotel Link → Smile PMS | D38: Real-time availability & rate from Hotel Link channel manager; Smile PMS reservation push; booking confirmation; restorable PMS direct connection. | E38: End-to-end booking flow live
B39: G.3 | C39: Persistent booking widget | D39: Sticky top-right CTA contextual per property ("Book Tee Time" / "Book Room"). Survives scroll. | E39: Sticky widget across all pages
B40: G.4 | C40: Villa lead capture | D40: Newsletter form + interest form for villa launch waitlist; pushed to CRM/CSV export. | E40: Lead capture + 3rd-party feed
B41: H · MULTI-LANGUAGE (VI / EN / KO)
B42: H.1 | C42: Translation framework | D42: Per-language URL structure (/vi /en /ko), language switcher, fallback rules, hreflang tags, locale-aware date/currency. | E42: Multi-language infrastructure
B43: H.2 | C43: Swiss-Bel identity priority for EN/KO | D43: Co-branded header on EN/KO surfaces "Swiss-Belresort Tuyen Lam" prominently for inbound brand recognition. | E43: Conditional branding rules
B44: H.3 | C44: Translation memory hand-off | D44: Translation export/import workflow (XLIFF or CSV) for SAM's translation vendor. Vendor work-out-of-scope. | E44: Translation tooling docs
B45: I · CONTENT MANAGEMENT SYSTEM
B46: I.1 | C46: Headless / hybrid CMS setup | D46: Property pages set to static (admin-only); marketing-managed content (Offers, Blog, News, banners, pop-ups, gallery) freely editable. | E46: CMS instance + admin roles
B47: I.2 | C47: Role-based access control | D47: Roles: Super-admin, Property Editor, Marketing, Translator, Read-only. Audit log. | E47: RBAC + audit
B48: I.3 | C48: Featured Offers Cards engine | D48: Schedule offers, target by property/audience, A/B variant slots, expiry control. | E48: Offers module
B49: I.4 | C49: Pop-up Campaign engine | D49: Large center modal + small left slide-in; schedule, target by URL/segment, frequency capping, dismiss persistence. | E49: Pop-up module
B50: I.5 | C50: Newsletter integration | D50: Form capture → Mailchimp / SendGrid / Klaviyo (one provider). Double opt-in. (Email vendor account by client.) | E50: Newsletter integration live
B51: J · SEO & ANALYTICS
B52: J.1 | C52: Technical SEO baseline | D52: Clean URLs · canonical · meta/OG · Open Graph images · sitemap.xml · robots.txt · hreflang · breadcrumb schema. | E52: SEO audit report (green)
B53: J.2 | C53: Schema markup (Hotel, Golf, Restaurant, Event) | D53: Structured data per property type for richer SERP snippets. | E53: Schema validation pass
B54: J.3 | C54: Google Analytics 4 + GTM | D54: GA4 property, GTM container, event taxonomy, booking-funnel events, source/medium taxonomy. | E54: GA4 + GTM live, events firing
B55: J.4 | C55: Heatmap & session replay | D55: Hotjar or Microsoft Clarity tag on key templates; sample size guidance. | E55: Tag live · sample dashboard
B56: J.5 | C56: 301 redirect map | D56: Full URL-by-URL map from 4 legacy domains to new URLs; bulk redirect rules; 404 catch & monitoring. | E56: 301 map + 404 monitor (90 days)
B57: K · PERFORMANCE, ACCESSIBILITY & TRUST
B58: K.1 | C58: Core Web Vitals optimisation | D58: LCP/INP/CLS green on mobile & desktop for top 10 templates. AVIF/WebP image pipeline. Lazy-load. Critical CSS. | E58: Lighthouse ≥ 90 mobile/desktop
B59: K.2 | C59: WCAG 2.1 AA accessibility | D59: Colour contrast, focus state, keyboard nav, ARIA roles for nav/modals/carousels, alt text framework. | E59: Accessibility audit pass
B60: K.3 | C60: Trust signal layer | D60: Award badges (Swiss-Bel certifications, golf awards), review aggregator widget, partner logos. | E60: Trust components in CMS
B61: K.4 | C61: Browser & device support matrix | D61: Modern evergreen browsers (Chrome, Edge, Safari, Firefox latest-2); iOS 15+; Android 10+; IE not supported. | E61: Documented support matrix
B62: L · SECURITY & COMPLIANCE
B63: L.1 | C63: Security hardening (OWASP Top 10) | D63: Input validation, output encoding, CSRF, secure session, security headers, dependency scanning. Closes posture issues from prior incident. | E63: OWASP checklist signed off
B64: L.2 | C64: Web Application Firewall + DDoS | D64: Cloudflare WAF or equivalent, rate-limit rules, bot mitigation. | E64: WAF rules live
B65: L.3 | C65: Privacy & cookie compliance | D65: Cookie consent banner (Vietnam PDPL + GDPR-aware EU/KR), preference center, privacy policy templates VI/EN/KO. | E65: Cookie consent live + policy
B66: L.4 | C66: Backup & disaster recovery | D66: Daily automated backups, weekly off-site, documented RTO/RPO (4h / 24h), restore tested. | E66: Backup runbook + restore drill
B67: L.5 | C67: Legacy site archive | D67: Static archive of 4 legacy sites + media (read-only) for compliance/historical reference before redirect cutover. | E67: Cold-storage archive bundle
B68: M · 360° VR INTEGRATION
B69: M.1 | C69: VR media re-integration | D69: Existing samtuyenlam.com.vn 360° media re-mounted as tab/modules inside Room Type pages, Property Galleries, and Experience pages. No standalone VR site. | E69: VR module embedded in 4+ pages
B70: N · LIVE CHAT
B71: N.1 | C71: Zalo OA + Facebook Messenger | D71: Persistent floating widget across all pages; conversation routing per property. | E71: Live chat widget live
B72: O · DOMAIN MIGRATION
B73: O.1 | C73: Domain cutover plan | D73: DNS swap, SSL provisioning, redirect deployment, search-console reverification across 4 legacy domains. 90-day monitoring of 404s & rankings. | E73: Cutover runbook executed
B74: P · QA, UAT & LAUNCH
B75: P.1 | C75: Cross-browser & device QA | D75: Test matrix: 5 browsers × 3 device classes × 3 languages = 45 surfaces. | E75: QA report (zero P1/P2 open)
B76: P.2 | C76: Booking-flow end-to-end test | D76: 3 booking systems × 3 user scenarios each = 9 happy-path + 6 edge-case scenarios. | E76: Booking QA sign-off
B77: P.3 | C77: UAT support | D77: Two structured UAT cycles with client team; bug triage; defect resolution. | E77: UAT sign-off
B78: P.4 | C78: Go-live & launch monitoring | D78: Coordinated go-live, real-time monitoring, rollback plan ready. | E78: Successful launch
B79: Q · TRAINING & KNOWLEDGE TRANSFER
B80: Q.1 | C80: CMS training workshops | D80: Two half-day sessions for marketing team: content publishing, offers/pop-ups, blog, media library. | E80: Trained team + recordings
B81: Q.2 | C81: Admin & operations handbook | D81: Written guides: CMS, deployment, backup/restore, escalation paths. | E81: Operations handbook (PDF)
B82: Q.3 | C82: Source code & asset handover | D82: Git repository transfer, design files, infrastructure-as-code, credential vault hand-off. | E82: Repository + key handover
B83: R · POST-LAUNCH HYPERCARE
B84: R.1 | C84: 4-week intensive hypercare | D84: Dedicated team on stand-by post-launch: bug triage <4h response, daily health checks, weekly status call. | E84: Stability sign-off after week 4

Sheet 4. Pricing — Build
B1: BLUE CORAL ▍ Powered by ADNS · 8/7D Phan Huy Ich, Tan Binh, Ho Chi Minh City · +84 979 477 101 · hello@bluecoral.vn
B3: Phase 1 — Design, Build & Launch — Detailed Pricing
B5: Blended rate: 19.25 USD / hour · FX reference: 1 USD = 26,000 VND · Hour cost: 500,500 VND/h · All figures incl. 10% VAT in Grand Total
B7: WORKSTREAM | C7: DELIVERABLE | D7: EFFORT (HOURS) | I7: PRICE (VND) | J7: PRICE (USD) | K7: QTY | L7: NOTES
D8: BA | E8: DESIGN | F8: DEV | G8: PM | H8: TOTAL
B9: A. Discovery & Foundation | C9: Information architecture & sitemap | D9: 12 | E9: 8 | G9: 4 | H9: =SUM(D9:G9) -> 24 | I9: =H9*19.25*26000*K9 -> 12012000 | J9: =I9/26000 -> 462 | K9: 1 | L9: Sitemap, URL strategy, hreflang map.
C10: Design system & component library | E10: 60 | F10: 16 | G10: 8 | H10: =SUM(D10:G10) -> 84 | I10: =H10*19.25*26000*K10 -> 42042000 | J10: =I10/26000 -> 1617 | K10: 1 | L10: Figma system: typography, colour, components, dark/light tokens.
B11: B. Brand Home | C11: Brand Home — master template (10 blocks) | D11: 8 | E11: 56 | F11: 48 | G11: 6 | H11: =SUM(D11:G11) -> 118 | I11: =H11*19.25*26000*K11 -> 59059000 | J11: =I11/26000 -> 2271.5 | K11: 1 | L11: Hero video, brand narrative, 3 gateways, 3 pillars, offers, audience links, gallery, blog, newsletter, footer.
B12: C. Golf Property | C12: Golf property overview (6 blocks) | D12: 6 | E12: 32 | F12: 28 | G12: 4 | H12: =SUM(D12:G12) -> 70 | I12: =H12*19.25*26000*K12 -> 35035000 | J12: =I12/26000 -> 1347.5 | K12: 1 | L12: Hero · Course intro · 18-Hole/Coaching/Club House · Lifestyle · Gallery + 360° · CTA.
C13: Club House sub-pages (Restaurant · Rooms · Pro Shop) | D13: 2 | E13: 18 | F13: 16 | G13: 3 | H13: =SUM(D13:G13) -> 39 | I13: =H13*19.25*26000*K13 -> 58558500 | J13: =I13/26000 -> 2252.25 | K13: 3 | L13: 3 sub-templates.
B14: D. Swiss-Belresort | C14: Resort property overview (7 blocks) | D14: 8 | E14: 40 | F14: 32 | G14: 6 | H14: =SUM(D14:G14) -> 86 | I14: =H14*19.25*26000*K14 -> 43043000 | J14: =I14/26000 -> 1655.5 | K14: 1 | L14: Hero w/ Swiss-Bel identity · 151-room intro · Room grid · Spa · Dining · MICE · Experiences · Gallery · CTA.
C15: Room Type detail pages | D15: 3 | E15: 24 | F15: 18 | G15: 3 | H15: =SUM(D15:G15) -> 48 | I15: =H15*19.25*26000*K15 -> 72072000 | J15: =I15/26000 -> 2772 | K15: 3 | L15: 3 room layouts: Deluxe MV/GV, Studio MV, Family Deluxe, King Suite, Royal Suite, Standard.
C16: Spa & Wellness sub-page | D16: 2 | E16: 16 | F16: 12 | G16: 2 | H16: =SUM(D16:G16) -> 32 | I16: =H16*19.25*26000*K16 -> 16016000 | J16: =I16/26000 -> 616 | K16: 1 | L16: Curated wellness journeys, not service list.
C17: Dining sub-page | D17: 2 | E17: 12 | F17: 10 | G17: 2 | H17: =SUM(D17:G17) -> 26 | I17: =H17*19.25*26000*K17 -> 13013000 | J17: =I17/26000 -> 500.5 | K17: 1 | L17: Restaurant & bar storytelling, menu module.
C18: MICE & Events sub-page | D18: 3 | E18: 16 | F18: 14 | G18: 3 | H18: =SUM(D18:G18) -> 36 | I18: =H18*19.25*26000*K18 -> 18018000 | J18: =I18/26000 -> 693 | K18: 1 | L18: Venue specs, capacity, RFP form.
B19: E. Villa (deferred launch) | C19: Villa teaser (Coming Soon) + lead form | D19: 4 | E19: 24 | F19: 12 | G19: 2 | H19: =SUM(D19:G19) -> 42 | I19: =H19*19.25*26000*K19 -> 21021000 | J19: =I19/26000 -> 808.5 | K19: 1 | L19: No live booking. Brand storytelling + waitlist capture.
C20: Villa Room Type design templates (design-only) | D20: 2 | E20: 32 | G20: 4 | H20: =SUM(D20:G20) -> 38 | I20: =H20*19.25*26000*K20 -> 57057000 | J20: =I20/26000 -> 2194.5 | K20: 3 | L20: Standard, Deluxe Lake/Garden View, Suite Lake View, +1. Build deferred.
B21: F. Shared Pages | C21: About Us — brand story | D21: 4 | E21: 16 | F21: 12 | G21: 2 | H21: =SUM(D21:G21) -> 34 | I21: =H21*19.25*26000*K21 -> 17017000 | J21: =I21/26000 -> 654.5 | K21: 1
C22: Experiences (Wellness · Golf · Healing) | D22: 4 | E22: 20 | F22: 18 | G22: 2 | H22: =SUM(D22:G22) -> 44 | I22: =H22*19.25*26000*K22 -> 22022000 | J22: =I22/26000 -> 847 | K22: 1 | L22: 3 editorial pillars shared across properties.
C23: Offers & Packages — filterable | D23: 4 | E23: 20 | F23: 22 | G23: 2 | H23: =SUM(D23:G23) -> 48 | I23: =H23*19.25*26000*K23 -> 24024000 | J23: =I23/26000 -> 924 | K23: 1 | L23: Filter by property × audience; CMS-driven cards.
C24: Blog / News — listing | D24: 2 | E24: 14 | F24: 18 | G24: 2 | H24: =SUM(D24:G24) -> 36 | I24: =H24*19.25*26000*K24 -> 18018000 | J24: =I24/26000 -> 693 | K24: 1
C25: Blog / News — article detail | D25: 2 | E25: 12 | F25: 12 | G25: 2 | H25: =SUM(D25:G25) -> 28 | I25: =H25*19.25*26000*K25 -> 14014000 | J25: =I25/26000 -> 539 | K25: 1
C26: Careers (with JobPosting schema) | D26: 2 | E26: 12 | F26: 14 | G26: 2 | H26: =SUM(D26:G26) -> 30 | I26: =H26*19.25*26000*K26 -> 15015000 | J26: =I26/26000 -> 577.5 | K26: 1
C27: Contact — property-routed forms (×3) | D27: 2 | E27: 14 | F27: 18 | G27: 2 | H27: =SUM(D27:G27) -> 36 | I27: =H27*19.25*26000*K27 -> 18018000 | J27: =I27/26000 -> 693 | K27: 1 | L27: Map, hotline, Zalo/Messenger embed.
C28: Search — site-wide | D28: 2 | E28: 10 | F28: 22 | G28: 2 | H28: =SUM(D28:G28) -> 36 | I28: =H28*19.25*26000*K28 -> 18018000 | J28: =I28/26000 -> 693 | K28: 1 | L28: Cross-property search index.
C29: Information pages (Privacy/Terms/Cookie/404/FAQ) | E29: 8 | F29: 8 | G29: 1 | H29: =SUM(D29:G29) -> 17 | I29: — | J29: — | K29: One-time | L29: 5 templates · mostly text.
B30: G. Booking Integrations | C30: Golf → VNPay payment flow | D30: 6 | F30: 32 | G30: 4 | H30: =SUM(D30:G30) -> 42 | I30: =H30*19.25*26000*K30 -> 21021000 | J30: =I30/26000 -> 808.5 | K30: 1 | L30: Tee-time, fee calc, VNPay, confirmation, PMS push.
C31: Swiss-Belresort → Hotel Link → Smile PMS | D31: 8 | F31: 40 | G31: 6 | H31: =SUM(D31:G31) -> 54 | I31: =H31*19.25*26000*K31 -> 27027000 | J31: =I31/26000 -> 1039.5 | K31: 1 | L31: Real-time avail/rate, reservation push, confirmation.
C32: Persistent booking widget (sticky) | D32: 2 | E32: 6 | F32: 12 | G32: 2 | H32: =SUM(D32:G32) -> 22 | I32: =H32*19.25*26000*K32 -> 11011000 | J32: =I32/26000 -> 423.5 | K32: 1 | L32: Top-right sticky CTA contextual per property.
C33: Villa lead capture → CRM/CSV | D33: 2 | F33: 10 | G33: 2 | H33: =SUM(D33:G33) -> 14 | I33: =H33*19.25*26000*K33 -> 7007000 | J33: =I33/26000 -> 269.5 | K33: 1 | L33: Form + webhook to client CRM.
B34: H. Multi-language | C34: Multi-language framework (VI/EN/KO) | D34: 4 | E34: 8 | F34: 36 | G34: 4 | H34: =SUM(D34:G34) -> 52 | I34: =H34*19.25*26000*K34 -> 26026000 | J34: =I34/26000 -> 1001 | K34: 1 | L34: URL structure, switcher, hreflang, locale-aware formatting.
B35: I. CMS | C35: CMS setup (headless/hybrid) + DB structure | D35: 12 | F35: 28 | G35: 6 | H35: =SUM(D35:G35) -> 46 | I35: — | J35: — | K35: 1 | L35: Multi-property data model, multi-language entries, media library.
C36: Role-based access control + audit log | D36: 8 | F36: 12 | G36: 2 | H36: =SUM(D36:G36) -> 22 | I36: =H36*19.25*26000*K36 -> 11011000 | J36: =I36/26000 -> 423.5 | K36: 1 | L36: Super-admin, Property Editor, Marketing, Translator, Read-only.
C37: Featured Offers Cards engine | D37: 4 | E37: 8 | F37: 18 | G37: 2 | H37: =SUM(D37:G37) -> 32 | I37: =H37*19.25*26000*K37 -> 16016000 | J37: =I37/26000 -> 616 | K37: 1 | L37: Schedule, target, A/B variants, expiry.
C38: Pop-up Campaign engine | D38: 4 | E38: 8 | F38: 22 | G38: 2 | H38: =SUM(D38:G38) -> 36 | I38: =H38*19.25*26000*K38 -> 18018000 | J38: =I38/26000 -> 693 | K38: 1 | L38: Large center modal + small left slide-in; schedule, target, frequency cap.
C39: Newsletter integration (one provider) | D39: 2 | E39: 4 | F39: 12 | G39: 2 | H39: =SUM(D39:G39) -> 20 | I39: =H39*19.25*26000*K39 -> 10010000 | J39: =I39/26000 -> 385 | K39: 1 | L39: Mailchimp/SendGrid/Klaviyo. Vendor account by client.
C40: Content & media migration plan | D40: 8 | F40: 12 | G40: 2 | H40: =SUM(D40:G40) -> 22 | I40: — | J40: — | K40: One-time | L40: Mapping from 4 legacy sites; asset re-encoding.
B41: J. SEO & Analytics | C41: Technical SEO baseline | D41: 4 | F41: 20 | G41: 2 | H41: =SUM(D41:G41) -> 26 | I41: =H41*19.25*26000*K41 -> 13013000 | J41: =I41/26000 -> 500.5 | K41: 1 | L41: Canonical, meta/OG, sitemap.xml, robots.txt, breadcrumb schema, hreflang.
C42: Schema markup (Hotel · Golf · Restaurant · Event) | D42: 2 | F42: 14 | G42: 2 | H42: =SUM(D42:G42) -> 18 | I42: =H42*19.25*26000*K42 -> 9009000 | J42: =I42/26000 -> 346.5 | K42: 1 | L42: Structured data for rich SERP snippets.
C43: GA4 + GTM event taxonomy | D43: 3 | F43: 14 | G43: 2 | H43: =SUM(D43:G43) -> 19 | I43: =H43*19.25*26000*K43 -> 9509500 | J43: =I43/26000 -> 365.75 | K43: 1 | L43: Booking-funnel events, source/medium, custom dimensions.
C44: Heatmap & session replay (Hotjar/Clarity) | D44: 1 | F44: 6 | G44: 1 | H44: =SUM(D44:G44) -> 8 | I44: =H44*19.25*26000*K44 -> 4004000 | J44: =I44/26000 -> 154 | K44: 1
C45: 301 redirect map (URL-by-URL) | D45: 8 | F45: 16 | G45: 4 | H45: =SUM(D45:G45) -> 28 | I45: =H45*19.25*26000*K45 -> 14014000 | J45: =I45/26000 -> 539 | K45: 1 | L45: Map across 4 legacy domains + bulk rules.
B46: K. Performance & A11y | C46: Core Web Vitals optimisation | D46: 2 | E46: 4 | F46: 24 | G46: 3 | H46: =SUM(D46:G46) -> 33 | I46: =H46*19.25*26000*K46 -> 16516500 | J46: =I46/26000 -> 635.25 | K46: 1 | L46: LCP/INP/CLS green; AVIF/WebP pipeline; critical CSS.
C47: WCAG 2.1 AA accessibility | D47: 4 | E47: 6 | F47: 18 | G47: 3 | H47: =SUM(D47:G47) -> 31 | I47: =H47*19.25*26000*K47 -> 15515500 | J47: =I47/26000 -> 596.75 | K47: 1 | L47: Contrast, focus, keyboard nav, ARIA, alt-text framework.
C48: Trust signal layer (awards · Swiss-Bel · reviews) | D48: 2 | E48: 8 | F48: 12 | G48: 2 | H48: =SUM(D48:G48) -> 24 | I48: =H48*19.25*26000*K48 -> 12012000 | J48: =I48/26000 -> 462 | K48: 1 | L48: CMS-managed badges & review aggregator widget.
B49: L. Security & Compliance | C49: Security hardening (OWASP Top 10) | D49: 3 | F49: 18 | G49: 3 | H49: =SUM(D49:G49) -> 24 | I49: =H49*19.25*26000*K49 -> 12012000 | J49: =I49/26000 -> 462 | K49: 1 | L49: Closes posture issues from prior incident.
C50: WAF + DDoS protection configuration | D50: 1 | F50: 8 | G50: 2 | H50: =SUM(D50:G50) -> 11 | I50: =H50*19.25*26000*K50 -> 5505500 | J50: =I50/26000 -> 211.75 | K50: 1
C51: Cookie consent + privacy policy (VI/EN/KO) | D51: 3 | E51: 4 | F51: 14 | G51: 2 | H51: =SUM(D51:G51) -> 23 | I51: =H51*19.25*26000*K51 -> 11511500 | J51: =I51/26000 -> 442.75 | K51: 1 | L51: Vietnam PDPL + GDPR-aware preference center.
C52: Backup & DR runbook + restore drill | D52: 2 | F52: 10 | G52: 2 | H52: =SUM(D52:G52) -> 14 | I52: — | J52: — | K52: One-time | L52: RTO 4h / RPO 24h; restore drill before go-live.
C53: Legacy site archive (4 domains, read-only) | D53: 2 | F53: 12 | G53: 2 | H53: =SUM(D53:G53) -> 16 | I53: — | J53: — | K53: One-time | L53: Static snapshot + media bundle for compliance.
B54: M. 360° VR | C54: 360° VR re-integration into property pages | D54: 6 | F54: 36 | G54: 6 | H54: =SUM(D54:G54) -> 48 | I54: =H54*19.25*26000*K54 -> 24024000 | J54: =I54/26000 -> 924 | K54: 1 | L54: Embed existing media as tabs/modules in Room Type + Gallery + Experiences.
B55: N. Live Chat | C55: Zalo OA + Facebook Messenger widget | D55: 2 | E55: 4 | F55: 5 | G55: 2 | H55: =SUM(D55:G55) -> 13 | I55: =H55*19.25*26000*K55 -> 6506500 | J55: =I55/26000 -> 250.25 | K55: 1
B56: O. Migration | C56: Domain cutover plan + 90-day 404 monitor | D56: 4 | F56: 20 | G56: 6 | H56: =SUM(D56:G56) -> 30 | I56: =H56*19.25*26000*K56 -> 15015000 | J56: =I56/26000 -> 577.5 | K56: 1 | L56: DNS, SSL, redirect deploy, search-console reverification.
B57: P. QA & Launch | C57: Cross-browser & device QA | D57: 8 | F57: 28 | G57: 4 | H57: =SUM(D57:G57) -> 40 | I57: =H57*19.25*26000*K57 -> 20020000 | J57: =I57/26000 -> 770 | K57: 1 | L57: 5 browsers × 3 device classes × 3 languages.
C58: UAT support (2 cycles) | D58: 8 | F58: 16 | G58: 6 | H58: =SUM(D58:G58) -> 30 | I58: — | J58: — | K58: 1
C59: Go-live & launch monitoring | D59: 2 | F59: 12 | G59: 4 | H59: =SUM(D59:G59) -> 18 | I59: — | J59: — | K59: One-time | L59: Coordinated go-live; rollback plan ready.
B60: Q. Training & Handover | C60: CMS training workshops (×2 half-day) | D60: 4 | F60: 6 | G60: 4 | H60: =SUM(D60:G60) -> 14 | I60: =H60*19.25*26000*K60 -> 7007000 | J60: =I60/26000 -> 269.5 | K60: 1 | L60: Recorded sessions for marketing team.
C61: Admin & operations handbook | D61: 8 | E61: 4 | F61: 4 | G61: 2 | H61: =SUM(D61:G61) -> 18 | I61: — | J61: — | K61: One-time | L61: PDF + searchable web doc.
C62: Source code + asset handover | D62: 2 | F62: 6 | G62: 2 | H62: =SUM(D62:G62) -> 10 | I62: — | J62: — | K62: One-time | L62: Git transfer, infra-as-code, credential vault.
B64: SUBTOTAL (before discount & VAT) | I64: =SUM(I9:I62) -> 935434500 | J64: =I64/26000 -> 35978.25
B65: Volume discount (10%) | I65: =-I64*0.1 -> -93543450 | J65: =I65/26000 -> -3597.825
B66: VAT (10%) | I66: / | J66: =I66/26000 -> #VALUE!
B67: GRAND TOTAL (VAT included) | I67: =I64+I65 -> 841891050 | J67: =I67/26000 -> 32380.425
B69: Effort estimates apply our blended team rate (Business Analysis, Visual Design, Engineering, Project Management). One-time items are fixed-fee. Volume discount of 15% reflects programme scale across three properties. Grand Total is VAT-inclusive.

Sheet 5. Pricing — Hosting
B1: BLUE CORAL ▍ Powered by ADNS · 8/7D Phan Huy Ich, Tan Binh, Ho Chi Minh City · +84 979 477 101 · hello@bluecoral.vn
B3: Phase 2 — Hosting & Managed Services (Year 1)
B5: Year-1 infrastructure and SLA-backed managed services. Hosted on enterprise cloud with daily backups, hardened security posture (post-incident baseline), and 20 hours of dedicated technical support per month.
B7: WORKSTREAM | C7: ITEM | D7: PRICE (VND) | E7: TERM | F7: DESCRIPTION
B8: Cloud Infrastructure | C8: Enterprise hosting — multi-site, high-traffic profile | D8: =2400000*12 -> 28800000 | E8: 12 Months | F8: CPU 4 cores · RAM 8 GB · SSD 120 GB · daily backup · weekly snapshot
C9: CDN — Cloudflare Pro (global edge, image optimisation) | D9: =600000*12 -> 7200000 | E9: 12 Months | F9: Tunes Core Web Vitals; AVIF/WebP; global cache; bot management
C10: SSL Wildcard certificate (all subdomains) | D10: 0 | E10: 12 Months | F10: Valued at 1,800,000 ₫ — included at no charge
C11: WAF + DDoS protection (application layer) | D11: 0 | E11: 12 Months | F11: Valued at 5,580,000 ₫ — included at no charge. Mandatory given prior incident posture.
B12: Managed Services | C12: 5 hours of technical support per month · Managed hosting & SSL · Daily backups + weekly off-site · Security & threat scans (weekly) · Uptime monitoring 99.9% SLA · Performance & SEO on-page tweaks · Priority response < 4 hours · Module configuration & consulting · Source-code & version control · Monthly performance report | D12: =2200000*12 -> 26400000 | E12: 12 Months | F12: 3 months free at start — valued 6,600,000 ₫
B13: Setup | C13: Initial migration & DNS cutover | D13: Free of charge | E13: — | F13: DNS swap from legacy hosts; SSL provisioning; first-deploy.
B15: SUBTOTAL (before discount & VAT) | D15: =SUM(D8:D13) -> 62400000
B16: VAT (10%) | D16: =SUM(D8:D9)*0.1 -> 3600000
B17: GRAND TOTAL — Phase 2 (VAT included) | D17: =SUM(D15:D16) -> 66000000
B19: Billing options — quarterly (default) or annual prepayment (additional 5% discount). Service term renewable annually. Third-party license fees (Hotel Link, VNPay, Hotjar, Zalo OA) are billed directly by the providers and are not included in this Phase 2 figure.

Sheet 6. Timeline
B1: BLUE CORAL ▍ Powered by ADNS · 8/7D Phan Huy Ich, Tan Binh, Ho Chi Minh City · +84 979 477 101 · hello@bluecoral.vn
B3: Project Timeline — 20-Week Build + 12-Month Operations
B5: WORKSTREAM | C5: W1 | D5: W2 | E5: W3 | F5: W4 | G5: W5 | H5: W6 | I5: W7 | J5: W8 | K5: W9 | L5: W10 | M5: W11 | N5: W12 | O5: W13 | P5: W14 | Q5: W15 | R5: W16 | S5: W17 | T5: W18 | U5: W19 | V5: W20 | W5: KEY DELIVERABLE
B6: Phase | C6: M0 · Discovery | E6: M1 · Design | K6: M2 · Build | Q6: M3 · Integrate | U6: M4 · Launch
B7: Discovery workshops | W7: Discovery report + asset audit
B8: Information architecture | W8: Sitemap & URL strategy approved
B9: Brand narrative | W9: Brand voice + content strategy
B10: Design system | W10: Design system in Figma
B11: Visual design — templates | W11: 14 templates approved
B12: Backend & CMS setup | W12: CMS + RBAC operational
B13: Frontend build | W13: Static build delivered
B14: Multi-language framework | W14: VI/EN/KO switching live
B15: Golf booking → VNPay | W15: Booking flow live
B16: Resort booking → Hotel Link | W16: Booking flow live
B17: 360° VR integration | W17: 360° embedded in pages
B18: Live chat · Analytics · SEO | W18: GA4 + chat + SEO baseline
... B25: Training & handover | W25: Trained team + handbook
B27: POST-LAUNCH — 4 weeks intensive hypercare (W21-W24) · then 12 months Managed Services with SLA & monthly performance reviews
B29: Legend: | D29: Discovery | G29: Design / Build | J29: Integration | M29: Launch

Sheet 7. Commercial Terms
B1: BLUE CORAL ▍ Powered by ADNS · 8/7D Phan Huy Ich, Tan Binh, Ho Chi Minh City · +84 979 477 101 · hello@bluecoral.vn
B3: Commercial Terms, Assumptions & Exclusions
B5: 01 · PAYMENT SCHEDULE — PHASE 1
B6: Milestone 1 — Kickoff | C6: 30% · Payable within 7 business days of contract signature.
B7: Milestone 2 — Design Approval | C7: 30% · Payable upon written acceptance of UI/UX visual design (end of M1).
B8: Milestone 3 — UAT Sign-off | C8: 30% · Payable upon UAT acceptance, prior to production launch (end of M3).
B9: Milestone 4 — Launch & Handover | C9: 10% · Payable within 14 business days of go-live and complete handover (end of M4).
B10: Phase 2 — Hosting & Support | C10: Quarterly billing in advance, OR annual prepayment with 5% additional discount.
B12: 02 · CHANGE REQUEST POLICY
B13: Minor changes | C13: Changes inside agreed scope (e.g. copy tweaks, image swaps, layout micro-adjustments within a delivered template) are handled at no additional charge during the active sprint.
B14: Scope changes | C14: Net-new pages, integrations, templates, or workflows are estimated separately and signed off as a Change Order before work begins. Billed at the blended rate.
B15: Design revisions | C15: Three rounds of design revisions are included per template. Additional rounds quoted at the blended rate.
B16: Scope freeze | C16: Scope and visual design are frozen at end of M1. Subsequent changes follow the Change Order process.
B18: 03 · WARRANTY & SUPPORT
B19: Post-launch warranty (90 days) | C19: Defects against agreed acceptance criteria fixed at no additional charge for 90 days from go-live.
B20: Hypercare (4 weeks) | C20: Dedicated team on standby immediately post-launch: <4-hour response on production incidents, daily health checks, weekly status call.
B21: Managed services (Phase 2) | C21: 20 hours of monthly support, priority response <4 hours, with full SLA defined in the Hosting & Managed Services schedule.
B23: 04 · ENGAGEMENT ASSUMPTIONS
B24: ✓ | C24: Client provides a single empowered decision-maker per workstream (Marketing, IT, Property GMs).
B25: ✓ | C25: Client provides master content in Vietnamese on agreed schedule. Each week of content delay extends launch by the equivalent duration.
B26: ✓ | C26: Client provides API credentials and signs vendor NDAs/agreements with VNPay, Hotel Link, Smile PMS, Zalo OA, Facebook in time for M3 integration.
B27: ✓ | C27: Client provides existing photo & video assets (current 360° media, brand photography, room photography) by end of M0.
B28: ✓ | C28: EN and KO translations are produced by Client's translation vendor using our XLIFF/CSV export. Translation execution is out-of-scope.
B29: ✓ | C29: Client appoints UAT testers for two structured cycles in M4.
B30: ✓ | C30: Hosting Phase 2 begins on go-live; first invoice issued within 7 days of launch.
B31: ✓ | C31: All pricing is in Vietnamese Dong (VND). USD figures are reference only at the FX rate stated.
B33: 05 · OUT OF SCOPE / EXCLUSIONS
B34: ✗ | C34: Third-party SaaS license fees (Hotel Link, VNPay merchant fees, Hotjar, Zalo OA premium, Mailchimp, font/stock asset licenses) — billed directly by providers.
B35: ✗ | C35: New filming, photography, drone capture, or 3D scans (for hero video and new room photography). Quoted separately if required.
B36: ✗ | C36: Content writing in Vietnamese (master content) and translation production into EN and KO.
B37: ✗ | C37: Ongoing SEO content marketing, paid media management, social media management — quoted as separate engagement.
B38: ✗ | C38: Property Management System (PMS) software licensing and configuration changes inside Smile PMS.
B39: ✗ | C39: Hardware procurement (servers, devices) and on-premise infrastructure changes.
B40: ✗ | C40: Custom mobile apps (iOS/Android). The website is fully responsive on mobile browsers.
B41: ✗ | C41: Loyalty programme platform, gift voucher engine, or third-party CRM integration beyond the Newsletter and Lead-capture handoff specified.
B42: ✗ | C42: Re-design or feature work after the 90-day warranty period — handled under Phase 2 Managed Services time pool or as a separate Change Order.
B44: 06 · INTELLECTUAL PROPERTY & CONFIDENTIALITY
B45: Custom code & design | C45: Upon final payment, all custom code and original design assets created specifically for SAM Tuyen Lam become the exclusive property of the Client.
B46: Third-party components | C46: Open-source libraries and third-party plug-ins remain under their original licenses (MIT, Apache 2.0, etc.). License compliance documentation provided at handover.
B47: Confidentiality | C47: Both parties agree to keep this proposal, the engagement, and all shared business information confidential for a period of 3 years from disclosure.
B48: Portfolio rights | C48: Blue Coral may reference the project in our portfolio (name, screenshots, public-facing case study) unless Client opts out in writing.
B50: 07 · ACCEPTANCE
B51: By signing below, both parties accept the scope, pricing, timeline, and commercial terms set out in this proposal and its referenced sheets.
B53: FOR BLUE CORAL (ADNS)
B54: Name: | C54: Mr. Nguyen
B55: Title: | C55: Managing Director
B56: Signature:
B57: Date:
B59: FOR SAM TUYEN LAM
B60: Name: | C60: ______________
B61: Title: | C61: Authorised Representative
B62: Signature:
B63: Date:
